optional_dependencies/__init__.py
optional_dependencies/_core.py
optional_dependencies/_version.py
optional_dependencies/_version.pyi
optional_dependencies/py.typed
optional_dependencies/utils.py
optional_dependencies-0.4.0.dist-info/METADATA
optional_dependencies-0.4.0.dist-info/WHEEL
optional_dependencies-0.4.0.dist-info/licenses/LICENSE
optional_dependencies-0.4.0.dist-info/RECORD
