Metadata-Version: 2.4
Name: optional_dependencies
Version: 0.4.0
Summary: Construct Checks for Optional Dependencies
Project-URL: Bug Tracker, https://github.com/GalacticDynamics/optional_dependencies/issues
Project-URL: Changelog, https://github.com/GalacticDynamics/optional_dependencies/releases
Project-URL: Discussions, https://github.com/GalacticDynamics/optional_dependencies/discussions
Project-URL: Homepage, https://github.com/GalacticDynamics/optional_dependencies
Author-email: GalacticDynamics Maintainers <nstarman@users.noreply.github.com>
License: Copyright 2024 GalacticDynamics Maintainers
License-File: LICENSE
Classifier: Development Status :: 1 - Planning
Classifier: Intended Audience :: Developers
Classifier: Intended Audience :: Science/Research
Classifier: License :: OSI Approved :: MIT License
Classifier: Operating System :: OS Independent
Classifier: Programming Language :: Python
Classifier: Programming Language :: Python :: 3
Classifier: Programming Language :: Python :: 3 :: Only
Classifier: Programming Language :: Python :: 3.9
Classifier: Programming Language :: Python :: 3.10
Classifier: Programming Language :: Python :: 3.11
Classifier: Programming Language :: Python :: 3.12
Classifier: Programming Language :: Python :: 3.13
Classifier: Topic :: Scientific/Engineering
Classifier: Typing :: Typed
Requires-Python: >=3.9
Requires-Dist: packaging>=23.2
